{
  "classname": null,
  "name": null,
  "animation": {
    "classname": null,
    "name": "AnimationManager",
    "actionlist": []
  },
  "dataScale": 1,
  "designHeight": 1136,
  "designWidth": 640,
  "textures": [],
  "texturesPng": [
    "images/img_142.png",
    "images/img_143.png",
    "button/btn_113.png",
    "button/btn_103.png",
    "images/img_110.png",
    "img_activity/images_03.jpg",
    "img_activity/btn_03.png"
  ],
  "version": "1.5.0.0",
  "widgetTree": {
    "classname": "Panel",
    "name": null,
    "children": [
      {
        "classname": "Panel",
        "name": null,
        "children": [
          {
            "classname": "ImageView",
            "name": null,
            "children": [
              {
                "classname": "Label",
                "name": null,
                "children": [],
                "options": {
                  "__type": "LabelSurrogate:#EditorCommon.JsonModel.Component.GUI",
                  "classname": "Label",
                  "name": "lbl_title",
                  "ZOrder": 0,
                  "actiontag": 51385085,
                  "anchorPointX": 0.5,
                  "anchorPointY": 0.5,
                  "classType": "CocoStudio.EngineAdapterWrap.CSLabel",
                  "colorB": 144,
                  "colorG": 225,
                  "colorR": 255,
                  "customProperty": "",
                  "flipX": false,
                  "flipY": false,
                  "height": 32,
                  "ignoreSize": true,
                  "layoutParameter": null,
                  "opacity": 255,
                  "positionPercentX": 0,
                  "positionPercentY": 0.0568181835,
                  "positionType": 0,
                  "rotation": 0,
                  "scaleX": 1,
                  "scaleY": 1,
                  "sizePercentX": 0.328947365,
                  "sizePercentY": 0.363636374,
                  "sizeType": 0,
                  "tag": 80485,
                  "touchAble": false,
                  "useMergedTexture": false,
                  "visible": true,
                  "width": 125,
                  "x": 0,
                  "y": 5,
                  "areaHeight": 0,
                  "areaWidth": 0,
                  "fontFile": null,
                  "fontName": "微软雅黑",
                  "fontSize": 25,
                  "hAlignment": 0,
                  "text": "我是购物狂",
                  "touchScaleEnable": false,
                  "vAlignment": 0
                }
              }
            ],
            "options": {
              "__type": "ImageViewSurrogate:#EditorCommon.JsonModel.Component.GUI",
              "classname": "ImageView",
              "name": "Image_4",
              "ZOrder": 0,
              "actiontag": 59458202,
              "anchorPointX": 0.5,
              "anchorPointY": 0.5,
              "classType": "CocoStudio.EngineAdapterWrap.CSImageView",
              "colorB": 255,
              "colorG": 255,
              "colorR": 255,
              "customProperty": "",
              "flipX": false,
              "flipY": false,
              "height": 88,
              "ignoreSize": true,
              "layoutParameter": null,
              "opacity": 255,
              "positionPercentX": 0.5125,
              "positionPercentY": 0.996739149,
              "positionType": 0,
              "rotation": 0,
              "scaleX": 1,
              "scaleY": 1,
              "sizePercentX": 0.59375,
              "sizePercentY": 0.09565217,
              "sizeType": 0,
              "tag": 80484,
              "touchAble": false,
              "useMergedTexture": false,
              "visible": true,
              "width": 380,
              "x": 328,
              "y": 917,
              "capInsetsHeight": 1,
              "capInsetsWidth": 1,
              "capInsetsX": 0,
              "capInsetsY": 0,
              "fileName": null,
              "fileNameData": {
                "path": "images/img_143.png",
                "plistFile": "",
                "resourceType": 0
              },
              "scale9Enable": false,
              "scale9Height": 88,
              "scale9Width": 380
            }
          },
          {
            "classname": "Button",
            "name": null,
            "children": [],
            "options": {
              "__type": "ButtonSurrogate:#EditorCommon.JsonModel.Component.GUI",
              "classname": "Button",
              "name": "btn_close",
              "ZOrder": 0,
              "actiontag": 44830087,
              "anchorPointX": 0.5,
              "anchorPointY": 0.5,
              "classType": "CocoStudio.EngineAdapterWrap.CSButton",
              "colorB": 255,
              "colorG": 255,
              "colorR": 255,
              "customProperty": "",
              "flipX": false,
              "flipY": false,
              "height": 65,
              "ignoreSize": true,
              "layoutParameter": null,
              "opacity": 255,
              "positionPercentX": 0.9421875,
              "positionPercentY": 0.9945652,
              "positionType": 0,
              "rotation": 0,
              "scaleX": 1,
              "scaleY": 1,
              "sizePercentX": 0.115625,
              "sizePercentY": 0.07065217,
              "sizeType": 0,
              "tag": 80486,
              "touchAble": true,
              "useMergedTexture": false,
              "visible": true,
              "width": 74,
              "x": 603,
              "y": 915,
              "capInsetsHeight": 1,
              "capInsetsWidth": 1,
              "capInsetsX": 0,
              "capInsetsY": 0,
              "disabled": null,
              "disabledData": {
                "path": null,
                "plistFile": null,
                "resourceType": 0
              },
              "fontName": "微软雅黑",
              "fontSize": 14,
              "fontType": 0,
              "normal": null,
              "normalData": {
                "path": "button/btn_113.png",
                "plistFile": "",
                "resourceType": 0
              },
              "pressed": null,
              "pressedData": {
                "path": null,
                "plistFile": null,
                "resourceType": 0
              },
              "scale9Enable": false,
              "scale9Height": 65,
              "scale9Width": 74,
              "text": "",
              "textColorB": 255,
              "textColorG": 255,
              "textColorR": 255
            }
          },
          {
            "classname": "Button",
            "name": null,
            "children": [],
            "options": {
              "__type": "ButtonSurrogate:#EditorCommon.JsonModel.Component.GUI",
              "classname": "Button",
              "name": "btn_shop",
              "ZOrder": 0,
              "actiontag": 817607,
              "anchorPointX": 0.5,
              "anchorPointY": 0.5,
              "classType": "CocoStudio.EngineAdapterWrap.CSButton",
              "colorB": 255,
              "colorG": 255,
              "colorR": 255,
              "customProperty": "",
              "flipX": false,
              "flipY": false,
              "height": 64,
              "ignoreSize": true,
              "layoutParameter": null,
              "opacity": 255,
              "positionPercentX": 0.5,
              "positionPercentY": 0.05869565,
              "positionType": 0,
              "rotation": 0,
              "scaleX": 1,
              "scaleY": 1,
              "sizePercentX": 0.23125,
              "sizePercentY": 0.0695652142,
              "sizeType": 0,
              "tag": 80487,
              "touchAble": true,
              "useMergedTexture": false,
              "visible": true,
              "width": 148,
              "x": 320,
              "y": 54,
              "capInsetsHeight": 1,
              "capInsetsWidth": 1,
              "capInsetsX": 0,
              "capInsetsY": 0,
              "disabled": null,
              "disabledData": {
                "path": null,
                "plistFile": null,
                "resourceType": 0
              },
              "fontName": "微软雅黑",
              "fontSize": 25,
              "fontType": 0,
              "normal": null,
              "normalData": {
                "path": "button/btn_103.png",
                "plistFile": "",
                "resourceType": 0
              },
              "pressed": null,
              "pressedData": {
                "path": null,
                "plistFile": null,
                "resourceType": 0
              },
              "scale9Enable": false,
              "scale9Height": 64,
              "scale9Width": 148,
              "text": "前往商城",
              "textColorB": 59,
              "textColorG": 56,
              "textColorR": 217
            }
          },
          {
            "classname": "Panel",
            "name": null,
            "children": [
              {
                "classname": "Label",
                "name": null,
                "children": [],
                "options": {
                  "__type": "LabelSurrogate:#EditorCommon.JsonModel.Component.GUI",
                  "classname": "Label",
                  "name": "lbl_time",
                  "ZOrder": 0,
                  "actiontag": 56114419,
                  "anchorPointX": 0.5,
                  "anchorPointY": 0.5,
                  "classType": "CocoStudio.EngineAdapterWrap.CSLabel",
                  "colorB": 248,
                  "colorG": 250,
                  "colorR": 247,
                  "customProperty": "",
                  "flipX": false,
                  "flipY": false,
                  "height": 27,
                  "ignoreSize": true,
                  "layoutParameter": null,
                  "opacity": 255,
                  "positionPercentX": 0.49666667,
                  "positionPercentY": 0.5,
                  "positionType": 0,
                  "rotation": 0,
                  "scaleX": 1,
                  "scaleY": 1,
                  "sizePercentX": 0.6766667,
                  "sizePercentY": 0.54,
                  "sizeType": 0,
                  "tag": 80496,
                  "touchAble": false,
                  "useMergedTexture": false,
                  "visible": true,
                  "width": 406,
                  "x": 298,
                  "y": 25,
                  "areaHeight": 0,
                  "areaWidth": 0,
                  "fontFile": null,
                  "fontName": "微软雅黑",
                  "fontSize": 20,
                  "hAlignment": 0,
                  "text": "限时活动时间：8月26日14:00至9月1日14:00",
                  "touchScaleEnable": false,
                  "vAlignment": 0
                }
              }
            ],
            "options": {
              "__type": "PanelSurrogate:#EditorCommon.JsonModel.Component.GUI",
              "classname": "Panel",
              "name": "pnl_item_1_0",
              "ZOrder": 0,
              "actiontag": 11335309,
              "anchorPointX": 0,
              "anchorPointY": 0,
              "classType": "CocoStudio.EngineAdapterWrap.CSPanel",
              "colorB": 255,
              "colorG": 255,
              "colorR": 255,
              "customProperty": "",
              "flipX": false,
              "flipY": false,
              "height": 50,
              "ignoreSize": false,
              "layoutParameter": null,
              "opacity": 255,
              "positionPercentX": 0.02656253,
              "positionPercentY": 0.897826,
              "positionType": 0,
              "rotation": 0,
              "scaleX": 1,
              "scaleY": 1,
              "sizePercentX": 0.9375,
              "sizePercentY": 0.0543478243,
              "sizeType": 0,
              "tag": 80495,
              "touchAble": true,
              "useMergedTexture": false,
              "visible": true,
              "width": 600,
              "x": 17,
              "y": 825,
              "adaptScreen": false,
              "backGroundImage": null,
              "backGroundImageData": {
                "path": "images/img_110.png",
                "plistFile": "",
                "resourceType": 0
              },
              "backGroundScale9Enable": true,
              "bgColorB": 255,
              "bgColorG": 200,
              "bgColorOpacity": 0,
              "bgColorR": 150,
              "bgEndColorB": 255,
              "bgEndColorG": 200,
              "bgEndColorR": 150,
              "bgStartColorB": 255,
              "bgStartColorG": 255,
              "bgStartColorR": 255,
              "capInsetsHeight": 8,
              "capInsetsWidth": 8,
              "capInsetsX": 14,
              "capInsetsY": 14,
              "clipAble": false,
              "colorType": 1,
              "layoutType": 0,
              "vectorX": 0,
              "vectorY": -0.5
            }
          },
          {
            "classname": "Panel",
            "name": null,
            "children": [
              {
                "classname": "ImageView",
                "name": null,
                "children": [
                  {
                    "classname": "Label",
                    "name": null,
                    "children": [],
                    "options": {
                      "__type": "LabelSurrogate:#EditorCommon.JsonModel.Component.GUI",
                      "classname": "Label",
                      "name": "lbl_left",
                      "ZOrder": 0,
                      "actiontag": 48785174,
                      "anchorPointX": 0.5,
                      "anchorPointY": 0.5,
                      "classType": "CocoStudio.EngineAdapterWrap.CSLabel",
                      "colorB": 18,
                      "colorG": 217,
                      "colorR": 26,
                      "customProperty": "",
                      "flipX": false,
                      "flipY": false,
                      "height": 30,
                      "ignoreSize": true,
                      "layoutParameter": null,
                      "opacity": 255,
                      "positionPercentX": 0,
                      "positionPercentY": 0.4627737,
                      "positionType": 0,
                      "rotation": 0,
                      "scaleX": 1,
                      "scaleY": 1,
                      "sizePercentX": 0.3644068,
                      "sizePercentY": 0.04379562,
                      "sizeType": 0,
                      "tag": 80501,
                      "touchAble": false,
                      "useMergedTexture": false,
                      "visible": true,
                      "width": 215,
                      "x": 0,
                      "y": 317,
                      "areaHeight": 0,
                      "areaWidth": 0,
                      "fontFile": null,
                      "fontName": "微软雅黑",
                      "fontSize": 22,
                      "hAlignment": 0,
                      "text": "我的地精之泪数量 : --",
                      "touchScaleEnable": false,
                      "vAlignment": 0
                    }
                  },
                  {
                    "classname": "Button",
                    "name": null,
                    "children": [],
                    "options": {
                      "__type": "ButtonSurrogate:#EditorCommon.JsonModel.Component.GUI",
                      "classname": "Button",
                      "name": "btn_change1",
                      "ZOrder": 0,
                      "actiontag": 45585384,
                      "anchorPointX": 0.5,
                      "anchorPointY": 0.5,
                      "classType": "CocoStudio.EngineAdapterWrap.CSButton",
                      "colorB": 255,
                      "colorG": 255,
                      "colorR": 255,
                      "customProperty": "",
                      "flipX": false,
                      "flipY": false,
                      "height": 50,
                      "ignoreSize": true,
                      "layoutParameter": null,
                      "opacity": 255,
                      "positionPercentX": -0.3237288,
                      "positionPercentY": -0.216058388,
                      "positionType": 0,
                      "rotation": 0,
                      "scaleX": 1,
                      "scaleY": 1,
                      "sizePercentX": 0.186440676,
                      "sizePercentY": 0.0729927,
                      "sizeType": 0,
                      "tag": 80502,
                      "touchAble": true,
                      "useMergedTexture": false,
                      "visible": true,
                      "width": 110,
                      "x": -191,
                      "y": -148,
                      "capInsetsHeight": 1,
                      "capInsetsWidth": 1,
                      "capInsetsX": 0,
                      "capInsetsY": 0,
                      "disabled": null,
                      "disabledData": {
                        "path": null,
                        "plistFile": null,
                        "resourceType": 0
                      },
                      "fontName": "微软雅黑",
                      "fontSize": 14,
                      "fontType": 0,
                      "normal": null,
                      "normalData": {
                        "path": "img_activity/btn_03.png",
                        "plistFile": "",
                        "resourceType": 0
                      },
                      "pressed": null,
                      "pressedData": {
                        "path": null,
                        "plistFile": null,
                        "resourceType": 0
                      },
                      "scale9Enable": false,
                      "scale9Height": 50,
                      "scale9Width": 110,
                      "text": "",
                      "textColorB": 255,
                      "textColorG": 255,
                      "textColorR": 255
                    }
                  },
                  {
                    "classname": "Button",
                    "name": null,
                    "children": [],
                    "options": {
                      "__type": "ButtonSurrogate:#EditorCommon.JsonModel.Component.GUI",
                      "classname": "Button",
                      "name": "btn_change2",
                      "ZOrder": 0,
                      "actiontag": 24776540,
                      "anchorPointX": 0.5,
                      "anchorPointY": 0.5,
                      "classType": "CocoStudio.EngineAdapterWrap.CSButton",
                      "colorB": 255,
                      "colorG": 255,
                      "colorR": 255,
                      "customProperty": "",
                      "flipX": false,
                      "flipY": false,
                      "height": 50,
                      "ignoreSize": true,
                      "layoutParameter": null,
                      "opacity": 255,
                      "positionPercentX": 0.00169491523,
                      "positionPercentY": -0.216058388,
                      "positionType": 0,
                      "rotation": 0,
                      "scaleX": 1,
                      "scaleY": 1,
                      "sizePercentX": 0.186440676,
                      "sizePercentY": 0.0729927,
                      "sizeType": 0,
                      "tag": 80503,
                      "touchAble": true,
                      "useMergedTexture": false,
                      "visible": true,
                      "width": 110,
                      "x": 1,
                      "y": -148,
                      "capInsetsHeight": 1,
                      "capInsetsWidth": 1,
                      "capInsetsX": 0,
                      "capInsetsY": 0,
                      "disabled": null,
                      "disabledData": {
                        "path": null,
                        "plistFile": null,
                        "resourceType": 0
                      },
                      "fontName": "微软雅黑",
                      "fontSize": 14,
                      "fontType": 0,
                      "normal": null,
                      "normalData": {
                        "path": "img_activity/btn_03.png",
                        "plistFile": "",
                        "resourceType": 0
                      },
                      "pressed": null,
                      "pressedData": {
                        "path": null,
                        "plistFile": null,
                        "resourceType": 0
                      },
                      "scale9Enable": false,
                      "scale9Height": 50,
                      "scale9Width": 110,
                      "text": "",
                      "textColorB": 255,
                      "textColorG": 255,
                      "textColorR": 255
                    }
                  },
                  {
                    "classname": "Button",
                    "name": null,
                    "children": [],
                    "options": {
                      "__type": "ButtonSurrogate:#EditorCommon.JsonModel.Component.GUI",
                      "classname": "Button",
                      "name": "btn_change3",
                      "ZOrder": 0,
                      "actiontag": 37784672,
                      "anchorPointX": 0.5,
                      "anchorPointY": 0.5,
                      "classType": "CocoStudio.EngineAdapterWrap.CSButton",
                      "colorB": 255,
                      "colorG": 255,
                      "colorR": 255,
                      "customProperty": "",
                      "flipX": false,
                      "flipY": false,
                      "height": 50,
                      "ignoreSize": true,
                      "layoutParameter": null,
                      "opacity": 255,
                      "positionPercentX": 0.328813553,
                      "positionPercentY": -0.216058388,
                      "positionType": 0,
                      "rotation": 0,
                      "scaleX": 1,
                      "scaleY": 1,
                      "sizePercentX": 0.186440676,
                      "sizePercentY": 0.0729927,
                      "sizeType": 0,
                      "tag": 80504,
                      "touchAble": true,
                      "useMergedTexture": false,
                      "visible": true,
                      "width": 110,
                      "x": 194,
                      "y": -148,
                      "capInsetsHeight": 1,
                      "capInsetsWidth": 1,
                      "capInsetsX": 0,
                      "capInsetsY": 0,
                      "disabled": null,
                      "disabledData": {
                        "path": null,
                        "plistFile": null,
                        "resourceType": 0
                      },
                      "fontName": "微软雅黑",
                      "fontSize": 14,
                      "fontType": 0,
                      "normal": null,
                      "normalData": {
                        "path": "img_activity/btn_03.png",
                        "plistFile": "",
                        "resourceType": 0
                      },
                      "pressed": null,
                      "pressedData": {
                        "path": null,
                        "plistFile": null,
                        "resourceType": 0
                      },
                      "scale9Enable": false,
                      "scale9Height": 50,
                      "scale9Width": 110,
                      "text": "",
                      "textColorB": 255,
                      "textColorG": 255,
                      "textColorR": 255
                    }
                  },
                  {
                    "classname": "Button",
                    "name": null,
                    "children": [],
                    "options": {
                      "__type": "ButtonSurrogate:#EditorCommon.JsonModel.Component.GUI",
                      "classname": "Button",
                      "name": "btn_change4",
                      "ZOrder": 0,
                      "actiontag": 36183900,
                      "anchorPointX": 0.5,
                      "anchorPointY": 0.5,
                      "classType": "CocoStudio.EngineAdapterWrap.CSButton",
                      "colorB": 255,
                      "colorG": 255,
                      "colorR": 255,
                      "customProperty": "",
                      "flipX": false,
                      "flipY": false,
                      "height": 50,
                      "ignoreSize": true,
                      "layoutParameter": null,
                      "opacity": 255,
                      "positionPercentX": 0.3237288,
                      "positionPercentY": -0.4,
                      "positionType": 0,
                      "rotation": 0,
                      "scaleX": 1,
                      "scaleY": 1,
                      "sizePercentX": 0.186440676,
                      "sizePercentY": 0.0729927,
                      "sizeType": 0,
                      "tag": 80505,
                      "touchAble": true,
                      "useMergedTexture": false,
                      "visible": true,
                      "width": 110,
                      "x": 191,
                      "y": -274,
                      "capInsetsHeight": 1,
                      "capInsetsWidth": 1,
                      "capInsetsX": 0,
                      "capInsetsY": 0,
                      "disabled": null,
                      "disabledData": {
                        "path": null,
                        "plistFile": null,
                        "resourceType": 0
                      },
                      "fontName": "微软雅黑",
                      "fontSize": 14,
                      "fontType": 0,
                      "normal": null,
                      "normalData": {
                        "path": "img_activity/btn_03.png",
                        "plistFile": "",
                        "resourceType": 0
                      },
                      "pressed": null,
                      "pressedData": {
                        "path": null,
                        "plistFile": null,
                        "resourceType": 0
                      },
                      "scale9Enable": false,
                      "scale9Height": 50,
                      "scale9Width": 110,
                      "text": "",
                      "textColorB": 255,
                      "textColorG": 255,
                      "textColorR": 255
                    }
                  }
                ],
                "options": {
                  "__type": "ImageViewSurrogate:#EditorCommon.JsonModel.Component.GUI",
                  "classname": "ImageView",
                  "name": "Image_205",
                  "ZOrder": 0,
                  "actiontag": 17465515,
                  "anchorPointX": 0.5,
                  "anchorPointY": 0.5,
                  "classType": "CocoStudio.EngineAdapterWrap.CSImageView",
                  "colorB": 255,
                  "colorG": 255,
                  "colorR": 255,
                  "customProperty": "",
                  "flipX": false,
                  "flipY": false,
                  "height": 685,
                  "ignoreSize": true,
                  "layoutParameter": null,
                  "opacity": 255,
                  "positionPercentX": 0.5,
                  "positionPercentY": 0.497866273,
                  "positionType": 0,
                  "rotation": 0,
                  "scaleX": 1,
                  "scaleY": 1,
                  "sizePercentX": 0.983333349,
                  "sizePercentY": 0.974395454,
                  "sizeType": 0,
                  "tag": 80498,
                  "touchAble": false,
                  "useMergedTexture": false,
                  "visible": true,
                  "width": 590,
                  "x": 300,
                  "y": 350,
                  "capInsetsHeight": 1,
                  "capInsetsWidth": 1,
                  "capInsetsX": 0,
                  "capInsetsY": 0,
                  "fileName": null,
                  "fileNameData": {
                    "path": "img_activity/images_03.jpg",
                    "plistFile": "",
                    "resourceType": 0
                  },
                  "scale9Enable": false,
                  "scale9Height": 685,
                  "scale9Width": 590
                }
              }
            ],
            "options": {
              "__type": "PanelSurrogate:#EditorCommon.JsonModel.Component.GUI",
              "classname": "Panel",
              "name": "pnl_item_0",
              "ZOrder": 0,
              "actiontag": 1940612,
              "anchorPointX": 0,
              "anchorPointY": 0,
              "classType": "CocoStudio.EngineAdapterWrap.CSPanel",
              "colorB": 255,
              "colorG": 255,
              "colorR": 255,
              "customProperty": "",
              "flipX": false,
              "flipY": false,
              "height": 703,
              "ignoreSize": false,
              "layoutParameter": null,
              "opacity": 255,
              "positionPercentX": 0.03125,
              "positionPercentY": 0.117934786,
              "positionType": 0,
              "rotation": 0,
              "scaleX": 1,
              "scaleY": 1,
              "sizePercentX": 0.9375,
              "sizePercentY": 0.7641304,
              "sizeType": 0,
              "tag": 80497,
              "touchAble": true,
              "useMergedTexture": false,
              "visible": true,
              "width": 600,
              "x": 20,
              "y": 108,
              "adaptScreen": false,
              "backGroundImage": null,
              "backGroundImageData": {
                "path": "images/img_110.png",
                "plistFile": "",
                "resourceType": 0
              },
              "backGroundScale9Enable": true,
              "bgColorB": 255,
              "bgColorG": 200,
              "bgColorOpacity": 0,
              "bgColorR": 150,
              "bgEndColorB": 255,
              "bgEndColorG": 200,
              "bgEndColorR": 150,
              "bgStartColorB": 255,
              "bgStartColorG": 255,
              "bgStartColorR": 255,
              "capInsetsHeight": 8,
              "capInsetsWidth": 8,
              "capInsetsX": 14,
              "capInsetsY": 14,
              "clipAble": false,
              "colorType": 1,
              "layoutType": 0,
              "vectorX": 0,
              "vectorY": -0.5
            }
          }
        ],
        "options": {
          "__type": "PanelSurrogate:#EditorCommon.JsonModel.Component.GUI",
          "classname": "Panel",
          "name": "Panel_3_0_0_0_0",
          "ZOrder": 0,
          "actiontag": 6287015,
          "anchorPointX": 0,
          "anchorPointY": 0,
          "classType": "CocoStudio.EngineAdapterWrap.CSPanel",
          "colorB": 255,
          "colorG": 255,
          "colorR": 255,
          "customProperty": "",
          "flipX": false,
          "flipY": false,
          "height": 920,
          "ignoreSize": false,
          "layoutParameter": {
            "classname": null,
            "name": null,
            "align": 8,
            "gravity": 0,
            "layoutEageType": 0,
            "layoutNormalHorizontal": 0,
            "layoutNormalVertical": 0,
            "layoutParentHorizontal": 0,
            "layoutParentVertical": 0,
            "marginDown": 0,
            "marginLeft": 0,
            "marginRight": 0,
            "marginTop": 0,
            "relativeName": "Panel_3_0_0_0_0",
            "relativeToName": "Panel_11",
            "type": 2
          },
          "opacity": 255,
          "positionPercentX": 0,
          "positionPercentY": 0,
          "positionType": 0,
          "rotation": 0,
          "scaleX": 1,
          "scaleY": 1,
          "sizePercentX": 1,
          "sizePercentY": 0.809859157,
          "sizeType": 0,
          "tag": 80483,
          "touchAble": true,
          "useMergedTexture": false,
          "visible": true,
          "width": 640,
          "x": 0,
          "y": 0,
          "adaptScreen": false,
          "backGroundImage": null,
          "backGroundImageData": {
            "path": "images/img_142.png",
            "plistFile": "",
            "resourceType": 0
          },
          "backGroundScale9Enable": true,
          "bgColorB": 255,
          "bgColorG": 200,
          "bgColorOpacity": 100,
          "bgColorR": 150,
          "bgEndColorB": 255,
          "bgEndColorG": 200,
          "bgEndColorR": 150,
          "bgStartColorB": 255,
          "bgStartColorG": 255,
          "bgStartColorR": 255,
          "capInsetsHeight": 25,
          "capInsetsWidth": 120,
          "capInsetsX": 51,
          "capInsetsY": 33,
          "clipAble": false,
          "colorType": 1,
          "layoutType": 0,
          "vectorX": 0,
          "vectorY": -0.5
        }
      }
    ],
    "options": {
      "__type": "PanelSurrogate:#EditorCommon.JsonModel.Component.GUI",
      "classname": "Panel",
      "name": "Panel_11",
      "ZOrder": 0,
      "actiontag": -1,
      "anchorPointX": 0,
      "anchorPointY": 0,
      "classType": "CocoStudio.EngineAdapterWrap.CSPanel",
      "colorB": 255,
      "colorG": 255,
      "colorR": 255,
      "customProperty": "",
      "flipX": false,
      "flipY": false,
      "height": 1136,
      "ignoreSize": false,
      "layoutParameter": null,
      "opacity": 255,
      "positionPercentX": 0,
      "positionPercentY": 0,
      "positionType": 0,
      "rotation": 0,
      "scaleX": 1,
      "scaleY": 1,
      "sizePercentX": 1,
      "sizePercentY": 1,
      "sizeType": 0,
      "tag": 80477,
      "touchAble": true,
      "useMergedTexture": false,
      "visible": true,
      "width": 640,
      "x": 0,
      "y": 0,
      "adaptScreen": true,
      "backGroundImage": null,
      "backGroundImageData": null,
      "backGroundScale9Enable": false,
      "bgColorB": 0,
      "bgColorG": 0,
      "bgColorOpacity": 193,
      "bgColorR": 0,
      "bgEndColorB": 255,
      "bgEndColorG": 200,
      "bgEndColorR": 150,
      "bgStartColorB": 255,
      "bgStartColorG": 255,
      "bgStartColorR": 255,
      "capInsetsHeight": 1,
      "capInsetsWidth": 1,
      "capInsetsX": 0,
      "capInsetsY": 0,
      "clipAble": false,
      "colorType": 1,
      "layoutType": 3,
      "vectorX": 0,
      "vectorY": -0.5
    }
  }
}