{
  "classname": null,
  "name": null,
  "animation": {
    "classname": null,
    "name": "AnimationManager",
    "actionlist": []
  },
  "dataScale": 1,
  "designHeight": 1136,
  "designWidth": 640,
  "textures": [],
  "texturesPng": [
    "loadingbar.png"
  ],
  "version": "1.5.0.0",
  "widgetTree": {
    "classname": "Panel",
    "name": null,
    "children": [
      {
        "classname": "Label",
        "name": null,
        "children": [],
        "options": {
          "__type": "LabelSurrogate:#EditorCommon.JsonModel.Component.GUI",
          "classname": "Label",
          "name": "lbl_msg",
          "ZOrder": 0,
          "actiontag": 2,
          "anchorPointX": 0.5,
          "anchorPointY": 0.5,
          "classType": "CocoStudio.EngineAdapterWrap.CSLabel",
          "colorB": 255,
          "colorG": 255,
          "colorR": 255,
          "customProperty": "",
          "flipX": false,
          "flipY": false,
          "height": 25,
          "ignoreSize": true,
          "layoutParameter": {
            "classname": null,
            "name": null,
            "align": 5,
            "gravity": 0,
            "layoutEageType": 0,
            "layoutNormalHorizontal": 0,
            "layoutNormalVertical": 0,
            "layoutParentHorizontal": 0,
            "layoutParentVertical": 0,
            "marginDown": 0,
            "marginLeft": 0,
            "marginRight": 0,
            "marginTop": 0,
            "relativeName": "lbl_msg",
            "relativeToName": "Panel_1",
            "type": 2
          },
          "opacity": 255,
          "positionPercentX": 0.5,
          "positionPercentY": 0.5,
          "positionType": 0,
          "rotation": 0,
          "scaleX": 1,
          "scaleY": 1,
          "sizePercentX": 0.15625,
          "sizePercentY": 0.0220070425,
          "sizeType": 0,
          "tag": 18949,
          "touchAble": false,
          "useMergedTexture": false,
          "visible": true,
          "width": 100,
          "x": 320,
          "y": 568,
          "areaHeight": 0,
          "areaWidth": 0,
          "fontFile": null,
          "fontName": "ttf/font.ttf",
          "fontSize": 25,
          "hAlignment": 0,
          "text": "更新状态",
          "touchScaleEnable": false,
          "vAlignment": 0
        }
      },
      {
        "classname": "LoadingBar",
        "name": null,
        "children": [],
        "options": {
          "__type": "LoadingBarSurrogate:#EditorCommon.JsonModel.Component.GUI",
          "classname": "LoadingBar",
          "name": "bar_process",
          "ZOrder": 0,
          "actiontag": 3,
          "anchorPointX": 0.5,
          "anchorPointY": 0.5,
          "classType": "CocoStudio.EngineAdapterWrap.CSLoadingBar",
          "colorB": 255,
          "colorG": 255,
          "colorR": 255,
          "customProperty": "",
          "flipX": false,
          "flipY": false,
          "height": 24,
          "ignoreSize": false,
          "layoutParameter": {
            "classname": null,
            "name": null,
            "align": 20,
            "gravity": 0,
            "layoutEageType": 0,
            "layoutNormalHorizontal": 0,
            "layoutNormalVertical": 0,
            "layoutParentHorizontal": 0,
            "layoutParentVertical": 0,
            "marginDown": 0,
            "marginLeft": 0,
            "marginRight": 0,
            "marginTop": 43,
            "relativeName": "bar_process",
            "relativeToName": "lbl_msg",
            "type": 2
          },
          "opacity": 255,
          "positionPercentX": 0.5,
          "positionPercentY": 0.440581,
          "positionType": 0,
          "rotation": 0,
          "scaleX": 1,
          "scaleY": 1,
          "sizePercentX": 0.5,
          "sizePercentY": 0.02112676,
          "sizeType": 0,
          "tag": 18950,
          "touchAble": false,
          "useMergedTexture": false,
          "visible": true,
          "width": 320,
          "x": 320,
          "y": 500,
          "capInsetsHeight": 1,
          "capInsetsWidth": 1,
          "capInsetsX": 0,
          "capInsetsY": 0,
          "direction": 0,
          "percent": 100,
          "scale9Enable": false,
          "texture": null,
          "textureData": {
            "path": "loadingbar.png",
            "plistFile": "",
            "resourceType": 0
          }
        }
      }
    ],
    "options": {
      "__type": "PanelSurrogate:#EditorCommon.JsonModel.Component.GUI",
      "classname": "Panel",
      "name": "Panel_1",
      "ZOrder": 0,
      "actiontag": -1,
      "anchorPointX": 0,
      "anchorPointY": 0,
      "classType": "CocoStudio.EngineAdapterWrap.CSPanel",
      "colorB": 255,
      "colorG": 255,
      "colorR": 255,
      "customProperty": "",
      "flipX": false,
      "flipY": false,
      "height": 1136,
      "ignoreSize": false,
      "layoutParameter": null,
      "opacity": 255,
      "positionPercentX": 0,
      "positionPercentY": 0,
      "positionType": 0,
      "rotation": 0,
      "scaleX": 1,
      "scaleY": 1,
      "sizePercentX": 1,
      "sizePercentY": 1,
      "sizeType": 0,
      "tag": 18948,
      "touchAble": true,
      "useMergedTexture": false,
      "visible": true,
      "width": 640,
      "x": 0,
      "y": 0,
      "adaptScreen": true,
      "backGroundImage": null,
      "backGroundImageData": null,
      "backGroundScale9Enable": false,
      "bgColorB": 0,
      "bgColorG": 0,
      "bgColorOpacity": 0,
      "bgColorR": 0,
      "bgEndColorB": 255,
      "bgEndColorG": 200,
      "bgEndColorR": 150,
      "bgStartColorB": 255,
      "bgStartColorG": 255,
      "bgStartColorR": 255,
      "capInsetsHeight": 1,
      "capInsetsWidth": 1,
      "capInsetsX": 0,
      "capInsetsY": 0,
      "clipAble": false,
      "colorType": 0,
      "layoutType": 3,
      "vectorX": 0,
      "vectorY": -0.5
    }
  }
}